anny/__init__.py
anny/anthropometry.py
anny/face_segmentation.py
anny/parameters_regressor.py
anny/paths.py
anny/shape_distribution.py
anny/data/template_mesh_internal_cavities.pth
anny/data/mpfb2/LICENSE.md
anny/data/mpfb2/3dobjs/base.obj
anny/data/mpfb2/mesh_metadata/basemesh_face_to_vertex_table.json.gz
anny/data/mpfb2/mesh_metadata/basemesh_vertex_groups.json
anny/data/mpfb2/mesh_metadata/basemesh_vertex_to_face_table.json.gz
anny/data/mpfb2/mesh_metadata/hm08.mirror
anny/data/mpfb2/mesh_metadata/hm08_config.json
anny/data/mpfb2/mesh_metadata/proxy_corrective.json
anny/data/mpfb2/node_trees/enhanced_skin.json
anny/data/mpfb2/node_trees/makeskin.json
anny/data/mpfb2/node_trees/procedural_eyes.json
anny/data/mpfb2/poses/cmu_mb_fk/t-pose.json
anny/data/mpfb2/poses/default_fk/t-pose.json
anny/data/mpfb2/poses/game_engine_fk/t-pose.json
anny/data/mpfb2/poses/game_engine_with_breast_fk/t-pose.json
anny/data/mpfb2/rigs/rigify/rig.human.json
anny/data/mpfb2/rigs/rigify/rig.human_toes.json
anny/data/mpfb2/rigs/rigify/weights.human_toes.json
anny/data/mpfb2/rigs/standard/rig.cmu_mb.json
anny/data/mpfb2/rigs/standard/rig.default.json
anny/data/mpfb2/rigs/standard/rig.default_no_toes.json
anny/data/mpfb2/rigs/standard/rig.game_engine.json
anny/data/mpfb2/rigs/standard/rig.game_engine_with_breast.json
anny/data/mpfb2/rigs/standard/rig.mixamo.json
anny/data/mpfb2/rigs/standard/weights.cmu_mb.json
anny/data/mpfb2/rigs/standard/weights.default.json
anny/data/mpfb2/rigs/standard/weights.game_engine.json
anny/data/mpfb2/rigs/standard/weights.game_engine_with_breast.json
anny/data/mpfb2/rigs/standard/weights.mixamo.json
anny/data/mpfb2/settings/enhanced_settings.default.json
anny/data/mpfb2/settings/eye_settings.default.json
anny/data/mpfb2/targets/target.json
anny/data/mpfb2/targets/_images/breast-dist-decr-incr.png
anny/data/mpfb2/targets/_images/breast-point-decr-incr.png
anny/data/mpfb2/targets/_images/breast-trans-down-up.png
anny-0.1.0.dist-info/licenses/LICENSE
anny-0.1.0.dist-info/METADATA
anny-0.1.0.dist-info/WHEEL
anny-0.1.0.dist-info/top_level.txt
anny-0.1.0.dist-info/RECORD
