Metadata-Version: 2.4
Name: anny
Version: 0.1.0
Summary: A parametric body model based on MakeHuman for PyTorch.
Author-email: Romain Brégier <romain.bregier@naverlabs.com>
License-File: LICENSE
Requires-Dist: torch>=2.0.0
Requires-Dist: roma>=1.5.2.1
Requires-Dist: numpy
Provides-Extra: examples
Requires-Dist: gradio; extra == "examples"
Requires-Dist: jsonargparse; extra == "examples"
Requires-Dist: trimesh; extra == "examples"
Provides-Extra: warp
Requires-Dist: warp-lang; extra == "warp"
Dynamic: license-file
